setup.py
pypal/__init__.py
pypal/http.py
pypal/resources.py
pypal.egg-info/PKG-INFO
pypal.egg-info/SOURCES.txt
pypal.egg-info/dependency_links.txt
pypal.egg-info/not-zip-safe
pypal.egg-info/requires.txt
pypal.egg-info/top_level.txt