Metadata-Version: 1.0
Name: pypal
Version: 0.1
Summary: PayPal API bindings in Python
Home-page: https://github.com/jarcoal/pypal
Author: Jared Morse
Author-email: jarcoal@gmail.com
License: BSD
Platform: UNKNOWN
Classifier: Programming Language :: Python
Classifier: Topic :: Software Development :: Libraries :: Python Modules
Classifier: Environment :: Web Environment
